tobacco/__init__.py
tobacco/_pype.py
tobacco-1.0.3.dist-info/LICENSE
tobacco-1.0.3.dist-info/METADATA
tobacco-1.0.3.dist-info/WHEEL
tobacco-1.0.3.dist-info/top_level.txt
tobacco-1.0.3.dist-info/RECORD
