Metadata-Version: 2.1
Name: tobacco
Version: 1.0.3
Summary: Function pipelines for python
Home-page: https://github.com/renzmann/tobacco
Author: Robert Enzmann
License: MIT
Platform: UNKNOWN
